vultr/__init__.py
vultr/utils.py
vultr/v1_account.py
vultr/v1_app.py
vultr/v1_backup.py
vultr/v1_dns.py
vultr/v1_firewall.py
vultr/v1_iso.py
vultr/v1_os.py
vultr/v1_plans.py
vultr/v1_regions.py
vultr/v1_reservedip.py
vultr/v1_server.py
vultr/v1_server_ipv4.py
vultr/v1_server_ipv6.py
vultr/v1_snapshot.py
vultr/v1_sshkey.py
vultr/v1_startupscript.py
vultr/vultr.py
vultr-1.0.1.dist-info/LICENSE.txt
vultr-1.0.1.dist-info/METADATA
vultr-1.0.1.dist-info/RECORD
vultr-1.0.1.dist-info/WHEEL
vultr-1.0.1.dist-info/top_level.txt
