Metadata-Version: 2.1
Name: vultr
Version: 1.0.1
Summary: Vultr.com API Client
Home-page: http://github.com/spry-group/python-vultr
Author: Darrel O'Pry
Author-email: darrel.opry@spry-group.com
License: The MIT License (MIT)
Requires-Dist: requests
